CHANGES.txt
DEPENDENCIES.txt
README.txt
bootstrap.py
buildout.cfg
setup.py
src/ks/__init__.py
src/ks.captcha.egg-info/PKG-INFO
src/ks.captcha.egg-info/SOURCES.txt
src/ks.captcha.egg-info/dependency_links.txt
src/ks.captcha.egg-info/namespace_packages.txt
src/ks.captcha.egg-info/not-zip-safe
src/ks.captcha.egg-info/requires.txt
src/ks.captcha.egg-info/top_level.txt
src/ks/captcha/DEMO.txt
src/ks/captcha/INSTALL.txt
src/ks/captcha/README.txt
src/ks/captcha/TODO.txt
src/ks/captcha/__init__.py
src/ks/captcha/captcha.py
src/ks/captcha/captcha.txt
src/ks/captcha/configure.zcml
src/ks/captcha/interfaces.py
src/ks/captcha/verdanai.ttf
src/ks/captcha/browser/__init__.py
src/ks/captcha/browser/captchaview.py
src/ks/captcha/browser/configure.zcml
src/ks/captcha/etc/ks.captcha-configure.zcml